toolwrapper.py
toolwrapper-0.3.0.dist-info/DESCRIPTION.rst
toolwrapper-0.3.0.dist-info/METADATA
toolwrapper-0.3.0.dist-info/RECORD
toolwrapper-0.3.0.dist-info/WHEEL
toolwrapper-0.3.0.dist-info/metadata.json
toolwrapper-0.3.0.dist-info/top_level.txt
